csv_processing/cleaning_processor.py
csv_processing/filling_gaps_processor.py
csv_processing/filling_gaps_strategy.py
csv_processing/models.py
csv_processing/parsing_processor.py
geotiff_processing/geotiff_processor.py
netcdf_processing/interpolation_service.py
netcdf_processing/netcdf_processor.py
relief_processing/relief_merging.py
ssp_models_compare/models_comparer.py
ShapeClimPy-0.0.1.dist-info/LICENSE
ShapeClimPy-0.0.1.dist-info/METADATA
ShapeClimPy-0.0.1.dist-info/WHEEL
ShapeClimPy-0.0.1.dist-info/top_level.txt
ShapeClimPy-0.0.1.dist-info/RECORD
