Metadata-Version: 2.1
Name: ShapeClimPy
Version: 0.0.1
Summary: ShapeClimPy is a library designed to simplify and automate the basic steps of processing and analyzing meteorological data
Author-email: Rupasov K <kirillrupasov143@gmail.com>
Project-URL: Homepage, https://github.com/CrazyFenX/ShapeClimPy
Classifier: Programming Language :: Python :: 3
Classifier: License :: OSI Approved :: MIT License
Classifier: Operating System :: OS Independent
Requires-Python: >=3.8
License-File: LICENSE
